{
  "id" : 118339,
  "handle" : "Manju02",
  "countHistoryTasks" : 27,
  "historyTasks" : null,
  "taskResult" : [ {
    "id" : 30138093,
    "postingDate" : "2020-08-21",
    "registrationDate" : "2020-08-24",
    "submissionDate" : "2020-08-27",
    "placement" : 8,
    "score" : 60.0
  }, {
    "id" : 30136672,
    "postingDate" : "2020-08-16",
    "registrationDate" : "2020-08-16",
    "submissionDate" : "2020-08-16",
    "placement" : 17,
    "score" : 20.0
  }, {
    "id" : 30136288,
    "postingDate" : "2020-08-07",
    "registrationDate" : "2020-08-07",
    "submissionDate" : null,
    "placement" : -1,
    "score" : 0.0
  }, {
    "id" : 30125701,
    "postingDate" : "2020-05-16",
    "registrationDate" : "2020-05-18",
    "submissionDate" : null,
    "placement" : -1,
    "score" : 0.0
  }, {
    "id" : 30124096,
    "postingDate" : "2020-05-04",
    "registrationDate" : "2020-05-05",
    "submissionDate" : "2020-05-05",
    "placement" : 4,
    "score" : 100.0
  }, {
    "id" : 30121999,
    "postingDate" : "2020-04-09",
    "registrationDate" : "2020-04-09",
    "submissionDate" : null,
    "placement" : -1,
    "score" : 0.0
  }, {
    "id" : 30119394,
    "postingDate" : "2020-04-01",
    "registrationDate" : "2020-04-01",
    "submissionDate" : "2020-04-09",
    "placement" : 31,
    "score" : 10.0
  }, {
    "id" : 30119755,
    "postingDate" : "2020-03-17",
    "registrationDate" : "2020-03-18",
    "submissionDate" : null,
    "placement" : -1,
    "score" : 0.0
  }, {
    "id" : 30119197,
    "postingDate" : "2020-03-12",
    "registrationDate" : "2020-03-13",
    "submissionDate" : "2020-03-16",
    "placement" : 10,
    "score" : 70.0
  }, {
    "id" : 30118158,
    "postingDate" : "2020-03-04",
    "registrationDate" : "2020-03-04",
    "submissionDate" : "2020-03-04",
    "placement" : -1,
    "score" : -1.0
  }, {
    "id" : 30117155,
    "postingDate" : "2020-03-01",
    "registrationDate" : "2020-03-03",
    "submissionDate" : "2020-03-03",
    "placement" : 5,
    "score" : 100.0
  }, {
    "id" : 30116609,
    "postingDate" : "2020-02-21",
    "registrationDate" : "2020-02-21",
    "submissionDate" : null,
    "placement" : -1,
    "score" : 0.0
  }, {
    "id" : 30113164,
    "postingDate" : "2020-01-22",
    "registrationDate" : "2020-01-22",
    "submissionDate" : "2020-01-26",
    "placement" : 5,
    "score" : 80.0
  }, {
    "id" : 30112499,
    "postingDate" : "2020-01-08",
    "registrationDate" : "2020-01-08",
    "submissionDate" : null,
    "placement" : -1,
    "score" : 0.0
  }, {
    "id" : 30111811,
    "postingDate" : "2019-12-25",
    "registrationDate" : "2019-12-25",
    "submissionDate" : null,
    "placement" : -1,
    "score" : 0.0
  }, {
    "id" : 30108777,
    "postingDate" : "2019-12-03",
    "registrationDate" : "2019-12-04",
    "submissionDate" : "2019-12-31",
    "placement" : 11,
    "score" : 100.0
  }, {
    "id" : 30111095,
    "postingDate" : "2019-12-24",
    "registrationDate" : "2019-12-24",
    "submissionDate" : "2019-12-27",
    "placement" : 6,
    "score" : 65.0
  }, {
    "id" : 30111809,
    "postingDate" : "2019-12-25",
    "registrationDate" : "2019-12-25",
    "submissionDate" : "2019-12-27",
    "placement" : 6,
    "score" : 70.0
  }, {
    "id" : 30110823,
    "postingDate" : "2019-12-15",
    "registrationDate" : "2019-12-16",
    "submissionDate" : "2019-12-17",
    "placement" : 8,
    "score" : 55.0
  }, {
    "id" : 30108902,
    "postingDate" : "2019-12-06",
    "registrationDate" : "2019-12-06",
    "submissionDate" : null,
    "placement" : -1,
    "score" : 0.0
  }, {
    "id" : 30107961,
    "postingDate" : "2019-11-25",
    "registrationDate" : "2019-11-25",
    "submissionDate" : "2019-11-28",
    "placement" : 2,
    "score" : 90.0
  }, {
    "id" : 30105578,
    "postingDate" : "2019-11-01",
    "registrationDate" : "2019-11-05",
    "submissionDate" : null,
    "placement" : -1,
    "score" : 0.0
  }, {
    "id" : 30105762,
    "postingDate" : "2019-11-05",
    "registrationDate" : "2019-11-05",
    "submissionDate" : "2019-11-08",
    "placement" : 3,
    "score" : 80.0
  }, {
    "id" : 30105597,
    "postingDate" : "2019-10-31",
    "registrationDate" : "2019-11-01",
    "submissionDate" : "2019-11-04",
    "placement" : 25,
    "score" : 10.0
  }, {
    "id" : 30104718,
    "postingDate" : "2019-10-22",
    "registrationDate" : "2019-10-22",
    "submissionDate" : "2019-10-24",
    "placement" : 4,
    "score" : 65.0
  }, {
    "id" : 30104233,
    "postingDate" : "2019-10-15",
    "registrationDate" : "2019-10-16",
    "submissionDate" : "2019-10-16",
    "placement" : 6,
    "score" : 70.0
  }, {
    "id" : 30103946,
    "postingDate" : "2019-10-07",
    "registrationDate" : "2019-10-09",
    "submissionDate" : "2019-10-10",
    "placement" : 2,
    "score" : 80.0
  } ]
}