{
  "id" : 86046,
  "handle" : "amber.j",
  "countHistoryTasks" : 222,
  "historyTasks" : null,
  "taskResult" : [ {
    "id" : 30064036,
    "postingDate" : "2018-03-27",
    "registrationDate" : "2018-03-27",
    "submissionDate" : null,
    "placement" : -1,
    "score" : 0.0
  }, {
    "id" : 30066817,
    "postingDate" : "2018-06-22",
    "registrationDate" : "2018-06-22",
    "submissionDate" : null,
    "placement" : -1,
    "score" : 0.0
  }, {
    "id" : 30066713,
    "postingDate" : "2018-06-25",
    "registrationDate" : "2018-06-25",
    "submissionDate" : null,
    "placement" : -1,
    "score" : 0.0
  }, {
    "id" : 30066922,
    "postingDate" : "2018-06-25",
    "registrationDate" : "2018-06-25",
    "submissionDate" : null,
    "placement" : -1,
    "score" : 0.0
  }, {
    "id" : 30066633,
    "postingDate" : "2018-06-19",
    "registrationDate" : "2018-06-19",
    "submissionDate" : null,
    "placement" : -1,
    "score" : 0.0
  }, {
    "id" : 30066809,
    "postingDate" : "2018-06-21",
    "registrationDate" : "2018-06-21",
    "submissionDate" : null,
    "placement" : -1,
    "score" : 0.0
  }, {
    "id" : 30066801,
    "postingDate" : "2018-06-21",
    "registrationDate" : "2018-06-21",
    "submissionDate" : null,
    "placement" : -1,
    "score" : 0.0
  }, {
    "id" : 30066631,
    "postingDate" : "2018-06-19",
    "registrationDate" : "2018-06-19",
    "submissionDate" : null,
    "placement" : -1,
    "score" : 0.0
  }, {
    "id" : 30066681,
    "postingDate" : "2018-06-22",
    "registrationDate" : "2018-06-22",
    "submissionDate" : null,
    "placement" : -1,
    "score" : 0.0
  }, {
    "id" : 30066819,
    "postingDate" : "2018-06-22",
    "registrationDate" : "2018-06-22",
    "submissionDate" : null,
    "placement" : -1,
    "score" : 0.0
  }, {
    "id" : 30066699,
    "postingDate" : "2018-06-21",
    "registrationDate" : "2018-06-21",
    "submissionDate" : null,
    "placement" : -1,
    "score" : 0.0
  }, {
    "id" : 30066696,
    "postingDate" : "2018-06-21",
    "registrationDate" : "2018-06-21",
    "submissionDate" : null,
    "placement" : -1,
    "score" : 0.0
  }, {
    "id" : 30066695,
    "postingDate" : "2018-06-21",
    "registrationDate" : "2018-06-21",
    "submissionDate" : null,
    "placement" : -1,
    "score" : 0.0
  }, {
    "id" : 30066598,
    "postingDate" : "2018-06-19",
    "registrationDate" : "2018-06-19",
    "submissionDate" : null,
    "placement" : -1,
    "score" : 0.0
  }, {
    "id" : 30066267,
    "postingDate" : "2018-06-11",
    "registrationDate" : "2018-06-11",
    "submissionDate" : null,
    "placement" : -1,
    "score" : 0.0
  }, {
    "id" : 30066266,
    "postingDate" : "2018-06-11",
    "registrationDate" : "2018-06-11",
    "submissionDate" : null,
    "placement" : -1,
    "score" : 0.0
  }, {
    "id" : 30066218,
    "postingDate" : "2018-06-11",
    "registrationDate" : "2018-06-11",
    "submissionDate" : null,
    "placement" : -1,
    "score" : 0.0
  }, {
    "id" : 30066204,
    "postingDate" : "2018-06-09",
    "registrationDate" : "2018-06-09",
    "submissionDate" : null,
    "placement" : -1,
    "score" : 0.0
  }, {
    "id" : 30066177,
    "postingDate" : "2018-06-08",
    "registrationDate" : "2018-06-08",
    "submissionDate" : null,
    "placement" : -1,
    "score" : 0.0
  }, {
    "id" : 30066176,
    "postingDate" : "2018-06-08",
    "registrationDate" : "2018-06-08",
    "submissionDate" : null,
    "placement" : -1,
    "score" : 0.0
  }, {
    "id" : 30066159,
    "postingDate" : "2018-06-07",
    "registrationDate" : "2018-06-07",
    "submissionDate" : null,
    "placement" : -1,
    "score" : 0.0
  }, {
    "id" : 30066120,
    "postingDate" : "2018-06-06",
    "registrationDate" : "2018-06-06",
    "submissionDate" : null,
    "placement" : -1,
    "score" : 0.0
  }, {
    "id" : 30066078,
    "postingDate" : "2018-06-07",
    "registrationDate" : "2018-06-07",
    "submissionDate" : null,
    "placement" : -1,
    "score" : 0.0
  }, {
    "id" : 30066135,
    "postingDate" : "2018-06-06",
    "registrationDate" : "2018-06-06",
    "submissionDate" : null,
    "placement" : -1,
    "score" : 0.0
  }, {
    "id" : 30066126,
    "postingDate" : "2018-06-06",
    "registrationDate" : "2018-06-06",
    "submissionDate" : null,
    "placement" : -1,
    "score" : 0.0
  }, {
    "id" : 30066124,
    "postingDate" : "2018-06-06",
    "registrationDate" : "2018-06-06",
    "submissionDate" : null,
    "placement" : -1,
    "score" : 0.0
  }, {
    "id" : 30066121,
    "postingDate" : "2018-06-06",
    "registrationDate" : "2018-06-06",
    "submissionDate" : null,
    "placement" : -1,
    "score" : 0.0
  }, {
    "id" : 30066123,
    "postingDate" : "2018-06-06",
    "registrationDate" : "2018-06-06",
    "submissionDate" : null,
    "placement" : -1,
    "score" : 0.0
  }, {
    "id" : 30066106,
    "postingDate" : "2018-06-09",
    "registrationDate" : "2018-06-09",
    "submissionDate" : null,
    "placement" : -1,
    "score" : 0.0
  }, {
    "id" : 30066016,
    "postingDate" : "2018-06-05",
    "registrationDate" : "2018-06-05",
    "submissionDate" : null,
    "placement" : -1,
    "score" : 0.0
  }, {
    "id" : 30066160,
    "postingDate" : "2018-06-07",
    "registrationDate" : "2018-06-07",
    "submissionDate" : null,
    "placement" : -1,
    "score" : 0.0
  }, {
    "id" : 30065950,
    "postingDate" : "2018-06-09",
    "registrationDate" : "2018-06-09",
    "submissionDate" : null,
    "placement" : -1,
    "score" : 0.0
  }, {
    "id" : 30066134,
    "postingDate" : "2018-06-07",
    "registrationDate" : "2018-06-07",
    "submissionDate" : null,
    "placement" : -1,
    "score" : 0.0
  }, {
    "id" : 30066141,
    "postingDate" : "2018-06-07",
    "registrationDate" : "2018-06-07",
    "submissionDate" : null,
    "placement" : -1,
    "score" : 0.0
  }, {
    "id" : 30066133,
    "postingDate" : "2018-06-06",
    "registrationDate" : "2018-06-06",
    "submissionDate" : null,
    "placement" : -1,
    "score" : 0.0
  }, {
    "id" : 30066122,
    "postingDate" : "2018-06-06",
    "registrationDate" : "2018-06-06",
    "submissionDate" : null,
    "placement" : -1,
    "score" : 0.0
  }, {
    "id" : 30064975,
    "postingDate" : "2018-06-06",
    "registrationDate" : "2018-06-06",
    "submissionDate" : null,
    "placement" : -1,
    "score" : 0.0
  }, {
    "id" : 30066075,
    "postingDate" : "2018-06-06",
    "registrationDate" : "2018-06-06",
    "submissionDate" : null,
    "placement" : -1,
    "score" : 0.0
  }, {
    "id" : 30065862,
    "postingDate" : "2018-06-01",
    "registrationDate" : "2018-06-01",
    "submissionDate" : null,
    "placement" : -1,
    "score" : 0.0
  }, {
    "id" : 30066030,
    "postingDate" : "2018-06-05",
    "registrationDate" : "2018-06-05",
    "submissionDate" : null,
    "placement" : -1,
    "score" : 0.0
  }, {
    "id" : 30066174,
    "postingDate" : "2018-06-08",
    "registrationDate" : "2018-06-08",
    "submissionDate" : null,
    "placement" : -1,
    "score" : 0.0
  }, {
    "id" : 30065876,
    "postingDate" : "2018-05-31",
    "registrationDate" : "2018-05-31",
    "submissionDate" : null,
    "placement" : -1,
    "score" : 0.0
  }, {
    "id" : 30066070,
    "postingDate" : "2018-06-05",
    "registrationDate" : "2018-06-05",
    "submissionDate" : null,
    "placement" : -1,
    "score" : 0.0
  }, {
    "id" : 30066067,
    "postingDate" : "2018-06-05",
    "registrationDate" : "2018-06-05",
    "submissionDate" : null,
    "placement" : -1,
    "score" : 0.0
  }, {
    "id" : 30066014,
    "postingDate" : "2018-06-05",
    "registrationDate" : "2018-06-05",
    "submissionDate" : null,
    "placement" : -1,
    "score" : 0.0
  }, {
    "id" : 30065911,
    "postingDate" : "2018-06-02",
    "registrationDate" : "2018-06-02",
    "submissionDate" : null,
    "placement" : -1,
    "score" : 0.0
  }, {
    "id" : 30065696,
    "postingDate" : "2018-05-26",
    "registrationDate" : "2018-05-26",
    "submissionDate" : null,
    "placement" : -1,
    "score" : 0.0
  }, {
    "id" : 30066009,
    "postingDate" : "2018-06-05",
    "registrationDate" : "2018-06-05",
    "submissionDate" : null,
    "placement" : -1,
    "score" : 0.0
  }, {
    "id" : 30065956,
    "postingDate" : "2018-06-03",
    "registrationDate" : "2018-06-03",
    "submissionDate" : null,
    "placement" : -1,
    "score" : 0.0
  }, {
    "id" : 30065885,
    "postingDate" : "2018-05-31",
    "registrationDate" : "2018-05-31",
    "submissionDate" : null,
    "placement" : -1,
    "score" : 0.0
  }, {
    "id" : 30065930,
    "postingDate" : "2018-06-01",
    "registrationDate" : "2018-06-01",
    "submissionDate" : null,
    "placement" : -1,
    "score" : 0.0
  }, {
    "id" : 30065940,
    "postingDate" : "2018-06-02",
    "registrationDate" : "2018-06-02",
    "submissionDate" : null,
    "placement" : -1,
    "score" : 0.0
  }, {
    "id" : 30065918,
    "postingDate" : "2018-06-01",
    "registrationDate" : "2018-06-01",
    "submissionDate" : null,
    "placement" : -1,
    "score" : 0.0
  }, {
    "id" : 30065704,
    "postingDate" : "2018-05-27",
    "registrationDate" : "2018-05-27",
    "submissionDate" : null,
    "placement" : -1,
    "score" : 0.0
  }, {
    "id" : 30065818,
    "postingDate" : "2018-05-30",
    "registrationDate" : "2018-05-30",
    "submissionDate" : "2018-06-06",
    "placement" : 1,
    "score" : 40.75
  }, {
    "id" : 30065874,
    "postingDate" : "2018-06-01",
    "registrationDate" : "2018-06-01",
    "submissionDate" : null,
    "placement" : -1,
    "score" : 0.0
  }, {
    "id" : 30065900,
    "postingDate" : "2018-06-01",
    "registrationDate" : "2018-06-01",
    "submissionDate" : null,
    "placement" : -1,
    "score" : 0.0
  }, {
    "id" : 30065909,
    "postingDate" : "2018-06-01",
    "registrationDate" : "2018-06-01",
    "submissionDate" : null,
    "placement" : -1,
    "score" : 0.0
  }, {
    "id" : 30065512,
    "postingDate" : "2018-05-26",
    "registrationDate" : "2018-05-26",
    "submissionDate" : null,
    "placement" : -1,
    "score" : 0.0
  }, {
    "id" : 30065939,
    "postingDate" : "2018-06-02",
    "registrationDate" : "2018-06-02",
    "submissionDate" : null,
    "placement" : -1,
    "score" : 0.0
  }, {
    "id" : 30065694,
    "postingDate" : "2018-05-26",
    "registrationDate" : "2018-05-26",
    "submissionDate" : null,
    "placement" : -1,
    "score" : 0.0
  }, {
    "id" : 30065921,
    "postingDate" : "2018-06-01",
    "registrationDate" : "2018-06-01",
    "submissionDate" : null,
    "placement" : -1,
    "score" : 0.0
  }, {
    "id" : 30065817,
    "postingDate" : "2018-05-30",
    "registrationDate" : "2018-05-30",
    "submissionDate" : null,
    "placement" : -1,
    "score" : 0.0
  }, {
    "id" : 30065867,
    "postingDate" : "2018-05-30",
    "registrationDate" : "2018-05-30",
    "submissionDate" : null,
    "placement" : -1,
    "score" : 0.0
  }, {
    "id" : 30065670,
    "postingDate" : "2018-05-24",
    "registrationDate" : "2018-05-24",
    "submissionDate" : null,
    "placement" : -1,
    "score" : 0.0
  }, {
    "id" : 30065652,
    "postingDate" : "2018-05-24",
    "registrationDate" : "2018-05-24",
    "submissionDate" : null,
    "placement" : -1,
    "score" : 0.0
  }, {
    "id" : 30065743,
    "postingDate" : "2018-05-29",
    "registrationDate" : "2018-05-29",
    "submissionDate" : null,
    "placement" : -1,
    "score" : 0.0
  }, {
    "id" : 30065643,
    "postingDate" : "2018-05-24",
    "registrationDate" : "2018-05-24",
    "submissionDate" : null,
    "placement" : -1,
    "score" : 0.0
  }, {
    "id" : 30065736,
    "postingDate" : "2018-05-28",
    "registrationDate" : "2018-05-28",
    "submissionDate" : null,
    "placement" : -1,
    "score" : 0.0
  }, {
    "id" : 30065733,
    "postingDate" : "2018-05-28",
    "registrationDate" : "2018-05-28",
    "submissionDate" : null,
    "placement" : -1,
    "score" : 0.0
  }, {
    "id" : 30065730,
    "postingDate" : "2018-05-28",
    "registrationDate" : "2018-05-28",
    "submissionDate" : null,
    "placement" : -1,
    "score" : 0.0
  }, {
    "id" : 30065752,
    "postingDate" : "2018-05-30",
    "registrationDate" : "2018-05-30",
    "submissionDate" : null,
    "placement" : -1,
    "score" : 0.0
  }, {
    "id" : 30065695,
    "postingDate" : "2018-05-26",
    "registrationDate" : "2018-05-26",
    "submissionDate" : null,
    "placement" : -1,
    "score" : 0.0
  }, {
    "id" : 30065875,
    "postingDate" : "2018-05-31",
    "registrationDate" : "2018-05-31",
    "submissionDate" : null,
    "placement" : -1,
    "score" : 0.0
  }, {
    "id" : 30065702,
    "postingDate" : "2018-05-26",
    "registrationDate" : "2018-05-26",
    "submissionDate" : null,
    "placement" : -1,
    "score" : 0.0
  }, {
    "id" : 30065634,
    "postingDate" : "2018-05-23",
    "registrationDate" : "2018-05-23",
    "submissionDate" : null,
    "placement" : -1,
    "score" : 0.0
  }, {
    "id" : 30065069,
    "postingDate" : "2018-05-24",
    "registrationDate" : "2018-05-24",
    "submissionDate" : null,
    "placement" : -1,
    "score" : 0.0
  }, {
    "id" : 30065357,
    "postingDate" : "2018-05-20",
    "registrationDate" : "2018-05-20",
    "submissionDate" : null,
    "placement" : -1,
    "score" : 0.0
  }, {
    "id" : 30065682,
    "postingDate" : "2018-05-25",
    "registrationDate" : "2018-05-25",
    "submissionDate" : null,
    "placement" : -1,
    "score" : 0.0
  }, {
    "id" : 30065480,
    "postingDate" : "2018-05-20",
    "registrationDate" : "2018-05-20",
    "submissionDate" : null,
    "placement" : -1,
    "score" : 0.0
  }, {
    "id" : 30065187,
    "postingDate" : "2018-05-23",
    "registrationDate" : "2018-05-23",
    "submissionDate" : null,
    "placement" : -1,
    "score" : 0.0
  }, {
    "id" : 30065505,
    "postingDate" : "2018-05-19",
    "registrationDate" : "2018-05-19",
    "submissionDate" : null,
    "placement" : -1,
    "score" : 0.0
  }, {
    "id" : 30065701,
    "postingDate" : "2018-05-26",
    "registrationDate" : "2018-05-26",
    "submissionDate" : null,
    "placement" : -1,
    "score" : 0.0
  }, {
    "id" : 30065002,
    "postingDate" : "2018-05-18",
    "registrationDate" : "2018-05-18",
    "submissionDate" : null,
    "placement" : -1,
    "score" : 0.0
  }, {
    "id" : 30065619,
    "postingDate" : "2018-05-23",
    "registrationDate" : "2018-05-23",
    "submissionDate" : null,
    "placement" : -1,
    "score" : 0.0
  }, {
    "id" : 30065552,
    "postingDate" : "2018-05-22",
    "registrationDate" : "2018-05-22",
    "submissionDate" : null,
    "placement" : -1,
    "score" : 0.0
  }, {
    "id" : 30065529,
    "postingDate" : "2018-05-20",
    "registrationDate" : "2018-05-20",
    "submissionDate" : null,
    "placement" : -1,
    "score" : 0.0
  }, {
    "id" : 30065580,
    "postingDate" : "2018-05-22",
    "registrationDate" : "2018-05-22",
    "submissionDate" : null,
    "placement" : -1,
    "score" : 0.0
  }, {
    "id" : 30065515,
    "postingDate" : "2018-05-19",
    "registrationDate" : "2018-05-19",
    "submissionDate" : null,
    "placement" : -1,
    "score" : 0.0
  }, {
    "id" : 30065527,
    "postingDate" : "2018-05-20",
    "registrationDate" : "2018-05-20",
    "submissionDate" : null,
    "placement" : -1,
    "score" : 0.0
  }, {
    "id" : 30065490,
    "postingDate" : "2018-05-18",
    "registrationDate" : "2018-05-18",
    "submissionDate" : null,
    "placement" : -1,
    "score" : 0.0
  }, {
    "id" : 30065205,
    "postingDate" : "2018-05-19",
    "registrationDate" : "2018-05-19",
    "submissionDate" : null,
    "placement" : -1,
    "score" : 0.0
  }, {
    "id" : 30065321,
    "postingDate" : "2018-05-15",
    "registrationDate" : "2018-05-15",
    "submissionDate" : null,
    "placement" : -1,
    "score" : 0.0
  }, {
    "id" : 30065526,
    "postingDate" : "2018-05-20",
    "registrationDate" : "2018-05-20",
    "submissionDate" : null,
    "placement" : -1,
    "score" : 0.0
  }, {
    "id" : 30065474,
    "postingDate" : "2018-05-18",
    "registrationDate" : "2018-05-18",
    "submissionDate" : null,
    "placement" : -1,
    "score" : 0.0
  }, {
    "id" : 30065418,
    "postingDate" : "2018-05-18",
    "registrationDate" : "2018-05-18",
    "submissionDate" : null,
    "placement" : -1,
    "score" : 0.0
  }, {
    "id" : 30065261,
    "postingDate" : "2018-05-14",
    "registrationDate" : "2018-05-14",
    "submissionDate" : null,
    "placement" : -1,
    "score" : 0.0
  }, {
    "id" : 30065443,
    "postingDate" : "2018-05-20",
    "registrationDate" : "2018-05-20",
    "submissionDate" : null,
    "placement" : -1,
    "score" : 0.0
  }, {
    "id" : 30065257,
    "postingDate" : "2018-05-14",
    "registrationDate" : "2018-05-14",
    "submissionDate" : null,
    "placement" : -1,
    "score" : 0.0
  }, {
    "id" : 30065484,
    "postingDate" : "2018-05-18",
    "registrationDate" : "2018-05-18",
    "submissionDate" : null,
    "placement" : -1,
    "score" : 0.0
  }, {
    "id" : 30065237,
    "postingDate" : "2018-05-13",
    "registrationDate" : "2018-05-13",
    "submissionDate" : null,
    "placement" : -1,
    "score" : 0.0
  }, {
    "id" : 30065422,
    "postingDate" : "2018-05-20",
    "registrationDate" : "2018-05-20",
    "submissionDate" : null,
    "placement" : -1,
    "score" : 0.0
  }, {
    "id" : 30065462,
    "postingDate" : "2018-05-17",
    "registrationDate" : "2018-05-17",
    "submissionDate" : null,
    "placement" : -1,
    "score" : 0.0
  }, {
    "id" : 30065368,
    "postingDate" : "2018-05-17",
    "registrationDate" : "2018-05-17",
    "submissionDate" : null,
    "placement" : -1,
    "score" : 0.0
  }, {
    "id" : 30065333,
    "postingDate" : "2018-05-17",
    "registrationDate" : "2018-05-17",
    "submissionDate" : null,
    "placement" : -1,
    "score" : 0.0
  }, {
    "id" : 30063672,
    "postingDate" : "2018-03-21",
    "registrationDate" : "2018-03-28",
    "submissionDate" : null,
    "placement" : -1,
    "score" : 0.0
  }, {
    "id" : 30063676,
    "postingDate" : "2018-03-30",
    "registrationDate" : "2018-03-30",
    "submissionDate" : null,
    "placement" : -1,
    "score" : 0.0
  }, {
    "id" : 30063675,
    "postingDate" : "2018-03-30",
    "registrationDate" : "2018-03-30",
    "submissionDate" : null,
    "placement" : -1,
    "score" : 0.0
  }, {
    "id" : 30063674,
    "postingDate" : "2018-03-30",
    "registrationDate" : "2018-03-30",
    "submissionDate" : null,
    "placement" : -1,
    "score" : 0.0
  }, {
    "id" : 30063673,
    "postingDate" : "2018-03-30",
    "registrationDate" : "2018-03-30",
    "submissionDate" : null,
    "placement" : -1,
    "score" : 0.0
  }, {
    "id" : 30065364,
    "postingDate" : "2018-05-16",
    "registrationDate" : "2018-05-16",
    "submissionDate" : null,
    "placement" : -1,
    "score" : 0.0
  }, {
    "id" : 30065446,
    "postingDate" : "2018-05-17",
    "registrationDate" : "2018-05-17",
    "submissionDate" : null,
    "placement" : -1,
    "score" : 0.0
  }, {
    "id" : 30065410,
    "postingDate" : "2018-05-16",
    "registrationDate" : "2018-05-16",
    "submissionDate" : null,
    "placement" : -1,
    "score" : 0.0
  }, {
    "id" : 30065314,
    "postingDate" : "2018-05-15",
    "registrationDate" : "2018-05-15",
    "submissionDate" : null,
    "placement" : -1,
    "score" : 0.0
  }, {
    "id" : 30065431,
    "postingDate" : "2018-05-17",
    "registrationDate" : "2018-05-17",
    "submissionDate" : null,
    "placement" : -1,
    "score" : 0.0
  }, {
    "id" : 30065330,
    "postingDate" : "2018-05-15",
    "registrationDate" : "2018-05-15",
    "submissionDate" : null,
    "placement" : -1,
    "score" : 0.0
  }, {
    "id" : 30065260,
    "postingDate" : "2018-05-14",
    "registrationDate" : "2018-05-14",
    "submissionDate" : null,
    "placement" : -1,
    "score" : 0.0
  }, {
    "id" : 30065230,
    "postingDate" : "2018-05-12",
    "registrationDate" : "2018-05-12",
    "submissionDate" : null,
    "placement" : -1,
    "score" : 0.0
  }, {
    "id" : 30065151,
    "postingDate" : "2018-05-09",
    "registrationDate" : "2018-05-09",
    "submissionDate" : null,
    "placement" : -1,
    "score" : 0.0
  }, {
    "id" : 30065239,
    "postingDate" : "2018-05-13",
    "registrationDate" : "2018-05-13",
    "submissionDate" : null,
    "placement" : -1,
    "score" : 0.0
  }, {
    "id" : 30065157,
    "postingDate" : "2018-05-09",
    "registrationDate" : "2018-05-09",
    "submissionDate" : null,
    "placement" : -1,
    "score" : 0.0
  }, {
    "id" : 30065293,
    "postingDate" : "2018-05-14",
    "registrationDate" : "2018-05-14",
    "submissionDate" : null,
    "placement" : -1,
    "score" : 0.0
  }, {
    "id" : 30065156,
    "postingDate" : "2018-05-09",
    "registrationDate" : "2018-05-09",
    "submissionDate" : null,
    "placement" : -1,
    "score" : 0.0
  }, {
    "id" : 30065232,
    "postingDate" : "2018-05-12",
    "registrationDate" : "2018-05-12",
    "submissionDate" : null,
    "placement" : -1,
    "score" : 0.0
  }, {
    "id" : 30065059,
    "postingDate" : "2018-05-07",
    "registrationDate" : "2018-05-07",
    "submissionDate" : null,
    "placement" : -1,
    "score" : 0.0
  }, {
    "id" : 30065058,
    "postingDate" : "2018-05-07",
    "registrationDate" : "2018-05-07",
    "submissionDate" : null,
    "placement" : -1,
    "score" : 0.0
  }, {
    "id" : 30065204,
    "postingDate" : "2018-05-12",
    "registrationDate" : "2018-05-12",
    "submissionDate" : null,
    "placement" : -1,
    "score" : 0.0
  }, {
    "id" : 30065048,
    "postingDate" : "2018-05-06",
    "registrationDate" : "2018-05-06",
    "submissionDate" : null,
    "placement" : -1,
    "score" : 0.0
  }, {
    "id" : 30065047,
    "postingDate" : "2018-05-06",
    "registrationDate" : "2018-05-06",
    "submissionDate" : null,
    "placement" : -1,
    "score" : 0.0
  }, {
    "id" : 30065236,
    "postingDate" : "2018-05-13",
    "registrationDate" : "2018-05-13",
    "submissionDate" : null,
    "placement" : -1,
    "score" : 0.0
  }, {
    "id" : 30065195,
    "postingDate" : "2018-05-11",
    "registrationDate" : "2018-05-11",
    "submissionDate" : null,
    "placement" : -1,
    "score" : 0.0
  }, {
    "id" : 30065006,
    "postingDate" : "2018-05-06",
    "registrationDate" : "2018-05-06",
    "submissionDate" : null,
    "placement" : -1,
    "score" : 0.0
  }, {
    "id" : 30065199,
    "postingDate" : "2018-05-13",
    "registrationDate" : "2018-05-13",
    "submissionDate" : null,
    "placement" : -1,
    "score" : 0.0
  }, {
    "id" : 30065008,
    "postingDate" : "2018-05-06",
    "registrationDate" : "2018-05-06",
    "submissionDate" : null,
    "placement" : -1,
    "score" : 0.0
  }, {
    "id" : 30065235,
    "postingDate" : "2018-05-12",
    "registrationDate" : "2018-05-12",
    "submissionDate" : null,
    "placement" : -1,
    "score" : 0.0
  }, {
    "id" : 30065096,
    "postingDate" : "2018-05-08",
    "registrationDate" : "2018-05-08",
    "submissionDate" : null,
    "placement" : -1,
    "score" : 0.0
  }, {
    "id" : 30064774,
    "postingDate" : "2018-05-08",
    "registrationDate" : "2018-05-08",
    "submissionDate" : null,
    "placement" : -1,
    "score" : 0.0
  }, {
    "id" : 30064989,
    "postingDate" : "2018-05-04",
    "registrationDate" : "2018-05-04",
    "submissionDate" : null,
    "placement" : -1,
    "score" : 0.0
  }, {
    "id" : 30065154,
    "postingDate" : "2018-05-09",
    "registrationDate" : "2018-05-09",
    "submissionDate" : null,
    "placement" : -1,
    "score" : 0.0
  }, {
    "id" : 30065152,
    "postingDate" : "2018-05-09",
    "registrationDate" : "2018-05-09",
    "submissionDate" : null,
    "placement" : -1,
    "score" : 0.0
  }, {
    "id" : 30065119,
    "postingDate" : "2018-05-08",
    "registrationDate" : "2018-05-08",
    "submissionDate" : null,
    "placement" : -1,
    "score" : 0.0
  }, {
    "id" : 30065144,
    "postingDate" : "2018-05-09",
    "registrationDate" : "2018-05-09",
    "submissionDate" : null,
    "placement" : -1,
    "score" : 0.0
  }, {
    "id" : 30065166,
    "postingDate" : "2018-05-10",
    "registrationDate" : "2018-05-10",
    "submissionDate" : null,
    "placement" : -1,
    "score" : 0.0
  }, {
    "id" : 30065165,
    "postingDate" : "2018-05-10",
    "registrationDate" : "2018-05-10",
    "submissionDate" : null,
    "placement" : -1,
    "score" : 0.0
  }, {
    "id" : 30065160,
    "postingDate" : "2018-05-09",
    "registrationDate" : "2018-05-09",
    "submissionDate" : null,
    "placement" : -1,
    "score" : 0.0
  }, {
    "id" : 30065103,
    "postingDate" : "2018-05-07",
    "registrationDate" : "2018-05-07",
    "submissionDate" : null,
    "placement" : -1,
    "score" : 0.0
  }, {
    "id" : 30064946,
    "postingDate" : "2018-05-03",
    "registrationDate" : "2018-05-03",
    "submissionDate" : null,
    "placement" : -1,
    "score" : 0.0
  }, {
    "id" : 30064942,
    "postingDate" : "2018-05-03",
    "registrationDate" : "2018-05-03",
    "submissionDate" : null,
    "placement" : -1,
    "score" : 0.0
  }, {
    "id" : 30065071,
    "postingDate" : "2018-05-07",
    "registrationDate" : "2018-05-07",
    "submissionDate" : null,
    "placement" : -1,
    "score" : 0.0
  }, {
    "id" : 30064735,
    "postingDate" : "2018-05-08",
    "registrationDate" : "2018-05-08",
    "submissionDate" : null,
    "placement" : -1,
    "score" : 0.0
  }, {
    "id" : 30065007,
    "postingDate" : "2018-05-06",
    "registrationDate" : "2018-05-06",
    "submissionDate" : null,
    "placement" : -1,
    "score" : 0.0
  }, {
    "id" : 30065005,
    "postingDate" : "2018-05-07",
    "registrationDate" : "2018-05-07",
    "submissionDate" : null,
    "placement" : -1,
    "score" : 0.0
  }, {
    "id" : 30065126,
    "postingDate" : "2018-05-08",
    "registrationDate" : "2018-05-08",
    "submissionDate" : null,
    "placement" : -1,
    "score" : 0.0
  }, {
    "id" : 30064962,
    "postingDate" : "2018-05-04",
    "registrationDate" : "2018-05-04",
    "submissionDate" : null,
    "placement" : -1,
    "score" : 0.0
  }, {
    "id" : 30065000,
    "postingDate" : "2018-05-05",
    "registrationDate" : "2018-05-05",
    "submissionDate" : null,
    "placement" : -1,
    "score" : 0.0
  }, {
    "id" : 30064857,
    "postingDate" : "2018-05-08",
    "registrationDate" : "2018-05-08",
    "submissionDate" : null,
    "placement" : -1,
    "score" : 0.0
  }, {
    "id" : 30064958,
    "postingDate" : "2018-05-03",
    "registrationDate" : "2018-05-03",
    "submissionDate" : null,
    "placement" : -1,
    "score" : 0.0
  }, {
    "id" : 30064902,
    "postingDate" : "2018-05-02",
    "registrationDate" : "2018-05-02",
    "submissionDate" : null,
    "placement" : -1,
    "score" : 0.0
  }, {
    "id" : 30064849,
    "postingDate" : "2018-05-04",
    "registrationDate" : "2018-05-04",
    "submissionDate" : null,
    "placement" : -1,
    "score" : 0.0
  }, {
    "id" : 30064816,
    "postingDate" : "2018-04-28",
    "registrationDate" : "2018-04-28",
    "submissionDate" : null,
    "placement" : -1,
    "score" : 0.0
  }, {
    "id" : 30065001,
    "postingDate" : "2018-05-05",
    "registrationDate" : "2018-05-05",
    "submissionDate" : null,
    "placement" : -1,
    "score" : 0.0
  }, {
    "id" : 30064967,
    "postingDate" : "2018-05-04",
    "registrationDate" : "2018-05-04",
    "submissionDate" : null,
    "placement" : -1,
    "score" : 0.0
  }, {
    "id" : 30064823,
    "postingDate" : "2018-04-29",
    "registrationDate" : "2018-04-29",
    "submissionDate" : null,
    "placement" : -1,
    "score" : 0.0
  }, {
    "id" : 30064886,
    "postingDate" : "2018-05-02",
    "registrationDate" : "2018-05-02",
    "submissionDate" : null,
    "placement" : -1,
    "score" : 0.0
  }, {
    "id" : 30064987,
    "postingDate" : "2018-05-04",
    "registrationDate" : "2018-05-04",
    "submissionDate" : null,
    "placement" : -1,
    "score" : 0.0
  }, {
    "id" : 30064867,
    "postingDate" : "2018-05-01",
    "registrationDate" : "2018-05-01",
    "submissionDate" : null,
    "placement" : -1,
    "score" : 0.0
  }, {
    "id" : 30064753,
    "postingDate" : "2018-04-26",
    "registrationDate" : "2018-04-26",
    "submissionDate" : null,
    "placement" : -1,
    "score" : 0.0
  }, {
    "id" : 30064879,
    "postingDate" : "2018-05-02",
    "registrationDate" : "2018-05-02",
    "submissionDate" : null,
    "placement" : -1,
    "score" : 0.0
  }, {
    "id" : 30064760,
    "postingDate" : "2018-04-26",
    "registrationDate" : "2018-04-26",
    "submissionDate" : null,
    "placement" : -1,
    "score" : 0.0
  }, {
    "id" : 30064759,
    "postingDate" : "2018-04-26",
    "registrationDate" : "2018-04-26",
    "submissionDate" : null,
    "placement" : -1,
    "score" : 0.0
  }, {
    "id" : 30064409,
    "postingDate" : "2018-04-28",
    "registrationDate" : "2018-04-28",
    "submissionDate" : null,
    "placement" : -1,
    "score" : 0.0
  }, {
    "id" : 30064919,
    "postingDate" : "2018-05-03",
    "registrationDate" : "2018-05-03",
    "submissionDate" : null,
    "placement" : -1,
    "score" : 0.0
  }, {
    "id" : 30064874,
    "postingDate" : "2018-05-01",
    "registrationDate" : "2018-05-01",
    "submissionDate" : null,
    "placement" : -1,
    "score" : 0.0
  }, {
    "id" : 30064825,
    "postingDate" : "2018-04-29",
    "registrationDate" : "2018-04-29",
    "submissionDate" : null,
    "placement" : -1,
    "score" : 0.0
  }, {
    "id" : 30064770,
    "postingDate" : "2018-04-27",
    "registrationDate" : "2018-04-27",
    "submissionDate" : null,
    "placement" : -1,
    "score" : 0.0
  }, {
    "id" : 30064739,
    "postingDate" : "2018-04-26",
    "registrationDate" : "2018-04-26",
    "submissionDate" : null,
    "placement" : -1,
    "score" : 0.0
  }, {
    "id" : 30064860,
    "postingDate" : "2018-05-01",
    "registrationDate" : "2018-05-01",
    "submissionDate" : null,
    "placement" : -1,
    "score" : 0.0
  }, {
    "id" : 30064733,
    "postingDate" : "2018-04-25",
    "registrationDate" : "2018-04-25",
    "submissionDate" : null,
    "placement" : -1,
    "score" : 0.0
  }, {
    "id" : 30064730,
    "postingDate" : "2018-04-25",
    "registrationDate" : "2018-04-25",
    "submissionDate" : null,
    "placement" : -1,
    "score" : 0.0
  }, {
    "id" : 30064865,
    "postingDate" : "2018-05-02",
    "registrationDate" : "2018-05-02",
    "submissionDate" : null,
    "placement" : -1,
    "score" : 0.0
  }, {
    "id" : 30064695,
    "postingDate" : "2018-04-24",
    "registrationDate" : "2018-04-24",
    "submissionDate" : null,
    "placement" : -1,
    "score" : 0.0
  }, {
    "id" : 30064638,
    "postingDate" : "2018-04-22",
    "registrationDate" : "2018-04-22",
    "submissionDate" : null,
    "placement" : -1,
    "score" : 0.0
  }, {
    "id" : 30064639,
    "postingDate" : "2018-04-23",
    "registrationDate" : "2018-04-23",
    "submissionDate" : null,
    "placement" : -1,
    "score" : 0.0
  }, {
    "id" : 30064773,
    "postingDate" : "2018-04-27",
    "registrationDate" : "2018-04-27",
    "submissionDate" : null,
    "placement" : -1,
    "score" : 0.0
  }, {
    "id" : 30064781,
    "postingDate" : "2018-04-26",
    "registrationDate" : "2018-04-26",
    "submissionDate" : null,
    "placement" : -1,
    "score" : 0.0
  }, {
    "id" : 30064832,
    "postingDate" : "2018-04-29",
    "registrationDate" : "2018-04-29",
    "submissionDate" : null,
    "placement" : -1,
    "score" : 0.0
  }, {
    "id" : 30064791,
    "postingDate" : "2018-04-30",
    "registrationDate" : "2018-04-30",
    "submissionDate" : null,
    "placement" : -1,
    "score" : 0.0
  }, {
    "id" : 30064786,
    "postingDate" : "2018-04-27",
    "registrationDate" : "2018-04-27",
    "submissionDate" : null,
    "placement" : -1,
    "score" : 0.0
  }, {
    "id" : 30064790,
    "postingDate" : "2018-04-27",
    "registrationDate" : "2018-04-27",
    "submissionDate" : null,
    "placement" : -1,
    "score" : 0.0
  }, {
    "id" : 30064626,
    "postingDate" : "2018-04-21",
    "registrationDate" : "2018-04-21",
    "submissionDate" : null,
    "placement" : -1,
    "score" : 0.0
  }, {
    "id" : 30064844,
    "postingDate" : "2018-04-30",
    "registrationDate" : "2018-04-30",
    "submissionDate" : null,
    "placement" : -1,
    "score" : 0.0
  }, {
    "id" : 30064811,
    "postingDate" : "2018-04-28",
    "registrationDate" : "2018-04-28",
    "submissionDate" : null,
    "placement" : -1,
    "score" : 0.0
  }, {
    "id" : 30064772,
    "postingDate" : "2018-04-27",
    "registrationDate" : "2018-04-27",
    "submissionDate" : null,
    "placement" : -1,
    "score" : 0.0
  }, {
    "id" : 30064737,
    "postingDate" : "2018-04-25",
    "registrationDate" : "2018-04-25",
    "submissionDate" : null,
    "placement" : -1,
    "score" : 0.0
  }, {
    "id" : 30064616,
    "postingDate" : "2018-04-20",
    "registrationDate" : "2018-04-20",
    "submissionDate" : null,
    "placement" : -1,
    "score" : 0.0
  }, {
    "id" : 30064738,
    "postingDate" : "2018-04-25",
    "registrationDate" : "2018-04-25",
    "submissionDate" : null,
    "placement" : -1,
    "score" : 0.0
  }, {
    "id" : 30064686,
    "postingDate" : "2018-04-24",
    "registrationDate" : "2018-04-24",
    "submissionDate" : null,
    "placement" : -1,
    "score" : 0.0
  }, {
    "id" : 30064547,
    "postingDate" : "2018-04-18",
    "registrationDate" : "2018-04-18",
    "submissionDate" : null,
    "placement" : -1,
    "score" : 0.0
  }, {
    "id" : 30064775,
    "postingDate" : "2018-04-26",
    "registrationDate" : "2018-04-26",
    "submissionDate" : null,
    "placement" : -1,
    "score" : 0.0
  }, {
    "id" : 30064624,
    "postingDate" : "2018-04-21",
    "registrationDate" : "2018-04-21",
    "submissionDate" : null,
    "placement" : -1,
    "score" : 0.0
  }, {
    "id" : 30064560,
    "postingDate" : "2018-04-19",
    "registrationDate" : "2018-04-19",
    "submissionDate" : null,
    "placement" : -1,
    "score" : 0.0
  }, {
    "id" : 30064537,
    "postingDate" : "2018-04-17",
    "registrationDate" : "2018-04-17",
    "submissionDate" : null,
    "placement" : -1,
    "score" : 0.0
  }, {
    "id" : 30064536,
    "postingDate" : "2018-04-17",
    "registrationDate" : "2018-04-17",
    "submissionDate" : null,
    "placement" : -1,
    "score" : 0.0
  }, {
    "id" : 30064535,
    "postingDate" : "2018-04-17",
    "registrationDate" : "2018-04-17",
    "submissionDate" : null,
    "placement" : -1,
    "score" : 0.0
  }, {
    "id" : 30063373,
    "postingDate" : "2018-03-23",
    "registrationDate" : "2018-03-23",
    "submissionDate" : null,
    "placement" : -1,
    "score" : 0.0
  }, {
    "id" : 30064687,
    "postingDate" : "2018-04-23",
    "registrationDate" : "2018-04-23",
    "submissionDate" : null,
    "placement" : -1,
    "score" : 0.0
  }, {
    "id" : 30064509,
    "postingDate" : "2018-04-16",
    "registrationDate" : "2018-04-16",
    "submissionDate" : null,
    "placement" : -1,
    "score" : 0.0
  }, {
    "id" : 30064531,
    "postingDate" : "2018-04-20",
    "registrationDate" : "2018-04-20",
    "submissionDate" : null,
    "placement" : -1,
    "score" : 0.0
  }, {
    "id" : 30064553,
    "postingDate" : "2018-04-19",
    "registrationDate" : "2018-04-19",
    "submissionDate" : null,
    "placement" : -1,
    "score" : 0.0
  }, {
    "id" : 30064559,
    "postingDate" : "2018-04-19",
    "registrationDate" : "2018-04-19",
    "submissionDate" : null,
    "placement" : -1,
    "score" : 0.0
  }, {
    "id" : 30064650,
    "postingDate" : "2018-04-23",
    "registrationDate" : "2018-04-23",
    "submissionDate" : null,
    "placement" : -1,
    "score" : 0.0
  }, {
    "id" : 30064501,
    "postingDate" : "2018-04-16",
    "registrationDate" : "2018-04-16",
    "submissionDate" : null,
    "placement" : -1,
    "score" : 0.0
  }, {
    "id" : 30064500,
    "postingDate" : "2018-04-16",
    "registrationDate" : "2018-04-16",
    "submissionDate" : null,
    "placement" : -1,
    "score" : 0.0
  }, {
    "id" : 30064558,
    "postingDate" : "2018-04-18",
    "registrationDate" : "2018-04-18",
    "submissionDate" : null,
    "placement" : -1,
    "score" : 0.0
  }, {
    "id" : 30064570,
    "postingDate" : "2018-04-19",
    "registrationDate" : "2018-04-19",
    "submissionDate" : null,
    "placement" : -1,
    "score" : 0.0
  }, {
    "id" : 30064483,
    "postingDate" : "2018-04-15",
    "registrationDate" : "2018-04-15",
    "submissionDate" : null,
    "placement" : -1,
    "score" : 0.0
  }, {
    "id" : 30064544,
    "postingDate" : "2018-04-17",
    "registrationDate" : "2018-04-17",
    "submissionDate" : null,
    "placement" : -1,
    "score" : 0.0
  }, {
    "id" : 30064557,
    "postingDate" : "2018-04-20",
    "registrationDate" : "2018-04-20",
    "submissionDate" : null,
    "placement" : -1,
    "score" : 0.0
  }, {
    "id" : 30064597,
    "postingDate" : "2018-04-20",
    "registrationDate" : "2018-04-20",
    "submissionDate" : null,
    "placement" : -1,
    "score" : 0.0
  }, {
    "id" : 30064555,
    "postingDate" : "2018-04-18",
    "registrationDate" : "2018-04-18",
    "submissionDate" : null,
    "placement" : -1,
    "score" : 0.0
  }, {
    "id" : 30064480,
    "postingDate" : "2018-04-14",
    "registrationDate" : "2018-04-14",
    "submissionDate" : null,
    "placement" : -1,
    "score" : 0.0
  }, {
    "id" : 30064471,
    "postingDate" : "2018-04-14",
    "registrationDate" : "2018-04-14",
    "submissionDate" : null,
    "placement" : -1,
    "score" : 0.0
  } ]
}