{
  "id" : 98264,
  "handle" : "brigittaforrai",
  "countHistoryTasks" : 20,
  "historyTasks" : null,
  "taskResult" : [ {
    "id" : 30151518,
    "postingDate" : "2020-11-17",
    "registrationDate" : "2020-11-17",
    "submissionDate" : null,
    "placement" : -1,
    "score" : 0.0
  }, {
    "id" : 30119201,
    "postingDate" : "2020-03-12",
    "registrationDate" : "2020-03-17",
    "submissionDate" : null,
    "placement" : -1,
    "score" : 0.0
  }, {
    "id" : 30119190,
    "postingDate" : "2020-03-12",
    "registrationDate" : "2020-03-17",
    "submissionDate" : null,
    "placement" : -1,
    "score" : 0.0
  }, {
    "id" : 30087933,
    "postingDate" : "2019-04-03",
    "registrationDate" : "2019-04-04",
    "submissionDate" : null,
    "placement" : -1,
    "score" : 0.0
  }, {
    "id" : 30087573,
    "postingDate" : "2019-03-27",
    "registrationDate" : "2019-03-28",
    "submissionDate" : "2019-04-01",
    "placement" : 3,
    "score" : 76.33333
  }, {
    "id" : 30079467,
    "postingDate" : "2019-01-17",
    "registrationDate" : "2019-01-20",
    "submissionDate" : null,
    "placement" : -1,
    "score" : 0.0
  }, {
    "id" : 30066016,
    "postingDate" : "2018-06-05",
    "registrationDate" : "2018-06-05",
    "submissionDate" : null,
    "placement" : -1,
    "score" : 0.0
  }, {
    "id" : 30065695,
    "postingDate" : "2018-05-26",
    "registrationDate" : "2018-05-26",
    "submissionDate" : null,
    "placement" : -1,
    "score" : 0.0
  }, {
    "id" : 30064861,
    "postingDate" : "2018-05-01",
    "registrationDate" : "2018-05-11",
    "submissionDate" : null,
    "placement" : -1,
    "score" : 0.0
  }, {
    "id" : 30065141,
    "postingDate" : "2018-05-08",
    "registrationDate" : "2018-05-11",
    "submissionDate" : null,
    "placement" : -1,
    "score" : 0.0
  }, {
    "id" : 30065237,
    "postingDate" : "2018-05-13",
    "registrationDate" : "2018-05-15",
    "submissionDate" : null,
    "placement" : -1,
    "score" : 0.0
  }, {
    "id" : 30065194,
    "postingDate" : "2018-05-11",
    "registrationDate" : "2018-05-11",
    "submissionDate" : null,
    "placement" : -1,
    "score" : 0.0
  }, {
    "id" : 30064616,
    "postingDate" : "2018-04-20",
    "registrationDate" : "2018-04-21",
    "submissionDate" : null,
    "placement" : -1,
    "score" : 0.0
  }, {
    "id" : 30063378,
    "postingDate" : "2018-03-07",
    "registrationDate" : "2018-03-12",
    "submissionDate" : null,
    "placement" : -1,
    "score" : 0.0
  }, {
    "id" : 30064184,
    "postingDate" : "2018-03-31",
    "registrationDate" : "2018-03-31",
    "submissionDate" : null,
    "placement" : -1,
    "score" : 0.0
  }, {
    "id" : 30063443,
    "postingDate" : "2018-03-08",
    "registrationDate" : "2018-03-09",
    "submissionDate" : null,
    "placement" : -1,
    "score" : 0.0
  }, {
    "id" : 30063444,
    "postingDate" : "2018-03-08",
    "registrationDate" : "2018-03-10",
    "submissionDate" : null,
    "placement" : -1,
    "score" : 0.0
  }, {
    "id" : 30063416,
    "postingDate" : "2018-03-07",
    "registrationDate" : "2018-03-12",
    "submissionDate" : "2018-03-12",
    "placement" : 3,
    "score" : 82.67
  }, {
    "id" : 30063066,
    "postingDate" : "2018-02-23",
    "registrationDate" : "2018-02-24",
    "submissionDate" : null,
    "placement" : -1,
    "score" : 0.0
  }, {
    "id" : 30063004,
    "postingDate" : "2018-02-19",
    "registrationDate" : "2018-02-19",
    "submissionDate" : "2018-02-22",
    "placement" : 1,
    "score" : 84.42
  } ]
}