{
  "id" : 98439,
  "handle" : "dwij",
  "countHistoryTasks" : 79,
  "historyTasks" : null,
  "taskResult" : [ {
    "id" : 30107461,
    "postingDate" : "2019-11-21",
    "registrationDate" : "2019-11-21",
    "submissionDate" : null,
    "placement" : -1,
    "score" : 0.0
  }, {
    "id" : 30104263,
    "postingDate" : "2019-10-14",
    "registrationDate" : "2019-10-14",
    "submissionDate" : null,
    "placement" : -1,
    "score" : 0.0
  }, {
    "id" : 30103980,
    "postingDate" : "2019-10-09",
    "registrationDate" : "2019-10-09",
    "submissionDate" : null,
    "placement" : -1,
    "score" : 0.0
  }, {
    "id" : 30103851,
    "postingDate" : "2019-10-04",
    "registrationDate" : "2019-10-04",
    "submissionDate" : null,
    "placement" : -1,
    "score" : 0.0
  }, {
    "id" : 30102713,
    "postingDate" : "2019-09-17",
    "registrationDate" : "2019-09-17",
    "submissionDate" : null,
    "placement" : -1,
    "score" : 0.0
  }, {
    "id" : 30102635,
    "postingDate" : "2019-09-18",
    "registrationDate" : "2019-09-18",
    "submissionDate" : null,
    "placement" : -1,
    "score" : 0.0
  }, {
    "id" : 30101981,
    "postingDate" : "2019-09-11",
    "registrationDate" : "2019-09-11",
    "submissionDate" : "2019-09-12",
    "placement" : -1,
    "score" : -1.0
  }, {
    "id" : 30093802,
    "postingDate" : "2019-06-18",
    "registrationDate" : "2019-06-19",
    "submissionDate" : null,
    "placement" : -1,
    "score" : 0.0
  }, {
    "id" : 30093711,
    "postingDate" : "2019-06-18",
    "registrationDate" : "2019-06-19",
    "submissionDate" : null,
    "placement" : -1,
    "score" : 0.0
  }, {
    "id" : 30092665,
    "postingDate" : "2019-06-06",
    "registrationDate" : "2019-06-06",
    "submissionDate" : null,
    "placement" : -1,
    "score" : 0.0
  }, {
    "id" : 30092582,
    "postingDate" : "2019-06-04",
    "registrationDate" : "2019-06-05",
    "submissionDate" : null,
    "placement" : -1,
    "score" : 0.0
  }, {
    "id" : 30092621,
    "postingDate" : "2019-06-05",
    "registrationDate" : "2019-06-05",
    "submissionDate" : null,
    "placement" : -1,
    "score" : 0.0
  }, {
    "id" : 30090755,
    "postingDate" : "2019-05-15",
    "registrationDate" : "2019-05-15",
    "submissionDate" : null,
    "placement" : -1,
    "score" : 0.0
  }, {
    "id" : 30090511,
    "postingDate" : "2019-05-12",
    "registrationDate" : "2019-05-13",
    "submissionDate" : null,
    "placement" : -1,
    "score" : 0.0
  }, {
    "id" : 30090537,
    "postingDate" : "2019-05-12",
    "registrationDate" : "2019-05-13",
    "submissionDate" : null,
    "placement" : -1,
    "score" : 0.0
  }, {
    "id" : 30089214,
    "postingDate" : "2019-05-14",
    "registrationDate" : "2019-05-14",
    "submissionDate" : null,
    "placement" : -1,
    "score" : 0.0
  }, {
    "id" : 30090473,
    "postingDate" : "2019-05-10",
    "registrationDate" : "2019-05-10",
    "submissionDate" : null,
    "placement" : -1,
    "score" : 0.0
  }, {
    "id" : 30088486,
    "postingDate" : "2019-04-14",
    "registrationDate" : "2019-04-14",
    "submissionDate" : null,
    "placement" : -1,
    "score" : 0.0
  }, {
    "id" : 30086698,
    "postingDate" : "2019-03-19",
    "registrationDate" : "2019-03-20",
    "submissionDate" : null,
    "placement" : -1,
    "score" : 0.0
  }, {
    "id" : 30086253,
    "postingDate" : "2019-03-13",
    "registrationDate" : "2019-03-14",
    "submissionDate" : null,
    "placement" : -1,
    "score" : 0.0
  }, {
    "id" : 30085188,
    "postingDate" : "2019-03-03",
    "registrationDate" : "2019-03-03",
    "submissionDate" : null,
    "placement" : -1,
    "score" : 0.0
  }, {
    "id" : 30085055,
    "postingDate" : "2019-03-06",
    "registrationDate" : "2019-03-06",
    "submissionDate" : null,
    "placement" : -1,
    "score" : 0.0
  }, {
    "id" : 30085306,
    "postingDate" : "2019-03-05",
    "registrationDate" : "2019-03-05",
    "submissionDate" : null,
    "placement" : -1,
    "score" : 0.0
  }, {
    "id" : 30084847,
    "postingDate" : "2019-02-27",
    "registrationDate" : "2019-02-27",
    "submissionDate" : null,
    "placement" : -1,
    "score" : 0.0
  }, {
    "id" : 30084589,
    "postingDate" : "2019-02-24",
    "registrationDate" : "2019-02-24",
    "submissionDate" : null,
    "placement" : -1,
    "score" : 0.0
  }, {
    "id" : 30084386,
    "postingDate" : "2019-02-20",
    "registrationDate" : "2019-02-21",
    "submissionDate" : null,
    "placement" : -1,
    "score" : 0.0
  }, {
    "id" : 30084838,
    "postingDate" : "2019-02-26",
    "registrationDate" : "2019-03-01",
    "submissionDate" : null,
    "placement" : -1,
    "score" : 0.0
  }, {
    "id" : 30082922,
    "postingDate" : "2019-02-06",
    "registrationDate" : "2019-02-06",
    "submissionDate" : null,
    "placement" : -1,
    "score" : 0.0
  }, {
    "id" : 30083415,
    "postingDate" : "2019-02-12",
    "registrationDate" : "2019-02-12",
    "submissionDate" : null,
    "placement" : -1,
    "score" : 0.0
  }, {
    "id" : 30077344,
    "postingDate" : "2018-12-18",
    "registrationDate" : "2018-12-18",
    "submissionDate" : null,
    "placement" : -1,
    "score" : 0.0
  }, {
    "id" : 30077297,
    "postingDate" : "2018-12-18",
    "registrationDate" : "2018-12-18",
    "submissionDate" : null,
    "placement" : -1,
    "score" : 0.0
  }, {
    "id" : 30071192,
    "postingDate" : "2018-12-20",
    "registrationDate" : "2018-12-20",
    "submissionDate" : null,
    "placement" : -1,
    "score" : 0.0
  }, {
    "id" : 30075410,
    "postingDate" : "2018-11-29",
    "registrationDate" : "2018-11-30",
    "submissionDate" : null,
    "placement" : -1,
    "score" : 0.0
  }, {
    "id" : 30075664,
    "postingDate" : "2018-12-03",
    "registrationDate" : "2018-12-04",
    "submissionDate" : null,
    "placement" : -1,
    "score" : 0.0
  }, {
    "id" : 30075671,
    "postingDate" : "2018-12-02",
    "registrationDate" : "2018-12-03",
    "submissionDate" : null,
    "placement" : -1,
    "score" : 0.0
  }, {
    "id" : 30075545,
    "postingDate" : "2018-11-30",
    "registrationDate" : "2018-11-30",
    "submissionDate" : null,
    "placement" : -1,
    "score" : 0.0
  }, {
    "id" : 30075466,
    "postingDate" : "2018-11-30",
    "registrationDate" : "2018-11-30",
    "submissionDate" : null,
    "placement" : -1,
    "score" : 0.0
  }, {
    "id" : 30075162,
    "postingDate" : "2018-11-26",
    "registrationDate" : "2018-11-26",
    "submissionDate" : null,
    "placement" : -1,
    "score" : 0.0
  }, {
    "id" : 30075073,
    "postingDate" : "2018-11-24",
    "registrationDate" : "2018-11-26",
    "submissionDate" : null,
    "placement" : -1,
    "score" : 0.0
  }, {
    "id" : 30072954,
    "postingDate" : "2018-10-19",
    "registrationDate" : "2018-10-19",
    "submissionDate" : null,
    "placement" : -1,
    "score" : 0.0
  }, {
    "id" : 30073131,
    "postingDate" : "2018-10-24",
    "registrationDate" : "2018-10-24",
    "submissionDate" : null,
    "placement" : -1,
    "score" : 0.0
  }, {
    "id" : 30071188,
    "postingDate" : "2018-10-16",
    "registrationDate" : "2018-10-16",
    "submissionDate" : null,
    "placement" : -1,
    "score" : 0.0
  }, {
    "id" : 30072494,
    "postingDate" : "2018-10-10",
    "registrationDate" : "2018-10-10",
    "submissionDate" : null,
    "placement" : -1,
    "score" : 0.0
  }, {
    "id" : 30071945,
    "postingDate" : "2018-10-04",
    "registrationDate" : "2018-10-04",
    "submissionDate" : null,
    "placement" : -1,
    "score" : 0.0
  }, {
    "id" : 30072455,
    "postingDate" : "2018-10-09",
    "registrationDate" : "2018-10-09",
    "submissionDate" : null,
    "placement" : -1,
    "score" : 0.0
  }, {
    "id" : 30072069,
    "postingDate" : "2018-09-30",
    "registrationDate" : "2018-10-01",
    "submissionDate" : null,
    "placement" : -1,
    "score" : 0.0
  }, {
    "id" : 30072067,
    "postingDate" : "2018-09-30",
    "registrationDate" : "2018-09-30",
    "submissionDate" : "2018-09-30",
    "placement" : -1,
    "score" : -1.0
  }, {
    "id" : 30072126,
    "postingDate" : "2018-10-03",
    "registrationDate" : "2018-10-03",
    "submissionDate" : null,
    "placement" : -1,
    "score" : 0.0
  }, {
    "id" : 30071274,
    "postingDate" : "2018-09-18",
    "registrationDate" : "2018-09-18",
    "submissionDate" : null,
    "placement" : -1,
    "score" : 0.0
  }, {
    "id" : 30071171,
    "postingDate" : "2018-09-15",
    "registrationDate" : "2018-09-15",
    "submissionDate" : null,
    "placement" : -1,
    "score" : 0.0
  }, {
    "id" : 30071273,
    "postingDate" : "2018-09-18",
    "registrationDate" : "2018-09-18",
    "submissionDate" : null,
    "placement" : -1,
    "score" : 0.0
  }, {
    "id" : 30070998,
    "postingDate" : "2018-09-11",
    "registrationDate" : "2018-09-11",
    "submissionDate" : null,
    "placement" : -1,
    "score" : 0.0
  }, {
    "id" : 30070548,
    "postingDate" : "2018-09-04",
    "registrationDate" : "2018-09-04",
    "submissionDate" : null,
    "placement" : -1,
    "score" : 0.0
  }, {
    "id" : 30070496,
    "postingDate" : "2018-09-03",
    "registrationDate" : "2018-09-03",
    "submissionDate" : null,
    "placement" : -1,
    "score" : 0.0
  }, {
    "id" : 30070230,
    "postingDate" : "2018-08-30",
    "registrationDate" : "2018-08-30",
    "submissionDate" : null,
    "placement" : -1,
    "score" : 0.0
  }, {
    "id" : 30070070,
    "postingDate" : "2018-08-27",
    "registrationDate" : "2018-08-28",
    "submissionDate" : null,
    "placement" : -1,
    "score" : 0.0
  }, {
    "id" : 30069806,
    "postingDate" : "2018-08-20",
    "registrationDate" : "2018-08-21",
    "submissionDate" : null,
    "placement" : -1,
    "score" : 0.0
  }, {
    "id" : 30069757,
    "postingDate" : "2018-08-19",
    "registrationDate" : "2018-08-19",
    "submissionDate" : null,
    "placement" : -1,
    "score" : 0.0
  }, {
    "id" : 30069734,
    "postingDate" : "2018-08-17",
    "registrationDate" : "2018-08-17",
    "submissionDate" : null,
    "placement" : -1,
    "score" : 0.0
  }, {
    "id" : 30068471,
    "postingDate" : "2018-08-17",
    "registrationDate" : "2018-08-18",
    "submissionDate" : null,
    "placement" : -1,
    "score" : 0.0
  }, {
    "id" : 30069379,
    "postingDate" : "2018-08-14",
    "registrationDate" : "2018-08-14",
    "submissionDate" : null,
    "placement" : -1,
    "score" : 0.0
  }, {
    "id" : 30068942,
    "postingDate" : "2018-08-07",
    "registrationDate" : "2018-08-07",
    "submissionDate" : null,
    "placement" : -1,
    "score" : 0.0
  }, {
    "id" : 30068755,
    "postingDate" : "2018-08-02",
    "registrationDate" : "2018-08-03",
    "submissionDate" : null,
    "placement" : -1,
    "score" : 0.0
  }, {
    "id" : 30068689,
    "postingDate" : "2018-08-02",
    "registrationDate" : "2018-08-03",
    "submissionDate" : "2018-08-07",
    "placement" : 1,
    "score" : 100.0
  }, {
    "id" : 30067211,
    "postingDate" : "2018-07-02",
    "registrationDate" : "2018-07-02",
    "submissionDate" : null,
    "placement" : -1,
    "score" : 0.0
  }, {
    "id" : 30065486,
    "postingDate" : "2018-05-18",
    "registrationDate" : "2018-05-22",
    "submissionDate" : null,
    "placement" : -1,
    "score" : 0.0
  }, {
    "id" : 30065552,
    "postingDate" : "2018-05-22",
    "registrationDate" : "2018-05-22",
    "submissionDate" : null,
    "placement" : -1,
    "score" : 0.0
  }, {
    "id" : 30065230,
    "postingDate" : "2018-05-12",
    "registrationDate" : "2018-05-12",
    "submissionDate" : null,
    "placement" : -1,
    "score" : 0.0
  }, {
    "id" : 30065204,
    "postingDate" : "2018-05-12",
    "registrationDate" : "2018-05-12",
    "submissionDate" : null,
    "placement" : -1,
    "score" : 0.0
  }, {
    "id" : 30064865,
    "postingDate" : "2018-05-02",
    "registrationDate" : "2018-05-02",
    "submissionDate" : null,
    "placement" : -1,
    "score" : 0.0
  }, {
    "id" : 30064773,
    "postingDate" : "2018-04-27",
    "registrationDate" : "2018-04-28",
    "submissionDate" : null,
    "placement" : -1,
    "score" : 0.0
  }, {
    "id" : 30064509,
    "postingDate" : "2018-04-16",
    "registrationDate" : "2018-04-16",
    "submissionDate" : null,
    "placement" : -1,
    "score" : 0.0
  }, {
    "id" : 30064407,
    "postingDate" : "2018-04-13",
    "registrationDate" : "2018-04-15",
    "submissionDate" : null,
    "placement" : -1,
    "score" : 0.0
  }, {
    "id" : 30064422,
    "postingDate" : "2018-04-12",
    "registrationDate" : "2018-04-13",
    "submissionDate" : null,
    "placement" : -1,
    "score" : 0.0
  }, {
    "id" : 30064319,
    "postingDate" : "2018-04-06",
    "registrationDate" : "2018-04-06",
    "submissionDate" : null,
    "placement" : -1,
    "score" : 0.0
  }, {
    "id" : 30064248,
    "postingDate" : "2018-04-04",
    "registrationDate" : "2018-04-04",
    "submissionDate" : null,
    "placement" : -1,
    "score" : 0.0
  }, {
    "id" : 30064223,
    "postingDate" : "2018-04-02",
    "registrationDate" : "2018-04-02",
    "submissionDate" : null,
    "placement" : -1,
    "score" : 0.0
  }, {
    "id" : 30062411,
    "postingDate" : "2018-01-23",
    "registrationDate" : "2018-01-23",
    "submissionDate" : null,
    "placement" : -1,
    "score" : 0.0
  }, {
    "id" : 30061789,
    "postingDate" : "2018-01-03",
    "registrationDate" : "2018-01-03",
    "submissionDate" : null,
    "placement" : -1,
    "score" : 0.0
  } ]
}